ComicInfo/ComicInfo.py
ComicInfo/__init__.py
ComicInfo/models/AgeRating.py
ComicInfo/models/ComicPageType.py
ComicInfo/models/Manga.py
ComicInfo/models/YesNo.py
ComicInfo/models/__init__.py
ComicInfo-0.0.0.dev0.dist-info/METADATA
ComicInfo-0.0.0.dev0.dist-info/WHEEL
ComicInfo-0.0.0.dev0.dist-info/top_level.txt
ComicInfo-0.0.0.dev0.dist-info/RECORD
